slop_mcp/__init__.py
slop_mcp/__main__.py
slop_mcp-0.9.3.dist-info/METADATA
slop_mcp-0.9.3.dist-info/WHEEL
slop_mcp-0.9.3.dist-info/entry_points.txt
slop_mcp-0.9.3.dist-info/licenses/LICENSE
slop_mcp-0.9.3.dist-info/RECORD
