Metadata-Version: 2.4
Name: slop-mcp
Version: 0.9.3
Summary: MCP server for orchestrating multiple MCP servers with progressive tool discovery
Project-URL: Homepage, https://github.com/standardbeagle/slop-mcp
Project-URL: Repository, https://github.com/standardbeagle/slop-mcp
Project-URL: Issues, https://github.com/standardbeagle/slop-mcp/issues
Author-email: StandardBeagle <dev@standardbeagle.com>
License-Expression: MIT
License-File: LICENSE
Keywords: ai,llm,mcp,model-context-protocol,tools
Classifier: Development Status :: 4 - Beta
Classifier: Environment :: Console
Classifier: Intended Audience :: Developers
Classifier: License :: OSI Approved :: MIT License
Classifier: Operating System :: OS Independent
Classifier: Programming Language :: Python :: 3
Classifier: Programming Language :: Python :: 3.8
Classifier: Programming Language :: Python :: 3.9
Classifier: Programming Language :: Python :: 3.10
Classifier: Programming Language :: Python :: 3.11
Classifier: Programming Language :: Python :: 3.12
Classifier: Topic :: Software Development :: Libraries
Requires-Python: >=3.8
Requires-Dist: httpx>=0.24.0
